{
"year":"2014",
"paper_type":"paper",
"contribution_type":"empirical",
"use_cases":"on-skin input",
"study_type":"elicitation study",
"study_setting":"lab",
"study_environment":"",
"study_stimulus":"video; animation; still images; prototype; demostration; none",
"demonstration_type":"researcher; peers; hands-on; none",
"measure_types":"objective; subjective; qualitative; quantitative",
"measure":"questionnaire; interview; video coding",
"questionnaire_type":"single-item; multi-item; open-ended; multiple choice; semantic differential",
"questionnaire":"audience-and-location; WEAR-scale; I-PANAS-SF; PANAS; Profita.2016; self-defined",
"perspective":"user"
}
